pyneuralnet/__init__.py
pyneuralnet/images/__init__.py
pyneuralnet/images/dataset_loader.py
pyneuralnet/images/train.py
pyneuralnet/images/models/CNN.py
pyneuralnet/images/models/GAN.py
pyneuralnet/images/models/__init__.py
PyNeuralNet-1.2.0.dist-info/LICENSE
PyNeuralNet-1.2.0.dist-info/METADATA
PyNeuralNet-1.2.0.dist-info/WHEEL
PyNeuralNet-1.2.0.dist-info/top_level.txt
PyNeuralNet-1.2.0.dist-info/RECORD
