Metadata-Version: 2.1
Name: PyNeuralNet
Version: 1.2.0
Summary: PyNeuralNet is a python library for prototyping and building neural networks. PyNeuralNet uses PyTorch as a computational backend for deep learning models.
Home-page: https://github.com/ItzLoghotXD/PyNeuralNet/
Download-URL: https://pypi.org/project/PyNeuralNet/
Author: ItzLoghotXD
Author-email: loghot.gamerz.official@gmail.com
Maintainer: ItzLoghotXD
Maintainer-email: loghot.gamerz.official@gmail.com
License: MIT License
Keywords: neural,network,ai,neural network,algorithm,loghot
License-File: LICENSE
Requires-Dist: torch >=2.1.1
Requires-Dist: torchvision >=0.16.1
Requires-Dist: matplotlib >=3.8.3
Requires-Dist: pillow >=10.1.0
